{"stat.damageDealt":90,"stat.crouchOneCm":352,"achievement.exploreAllBiomes":{"value":0,"progress":["Extreme Hills+","Extreme Hills","River"]},"achievement.openInventory":2,"stat.useItem.minecraft.bedrock":10,"stat.useItem.minecraft.planks":6,"stat.flyOneCm":241700,"stat.drop":1,"stat.useItem.minecraft.stone":3,"stat.timeSinceDeath":22272,"stat.playOneMinute":22272,"stat.leaveGame":2,"stat.killEntity.Spider":1,"stat.diveOneCm":1460,"stat.useItem.minecraft.wool":6,"stat.jump":22,"stat.walkOneCm":30566,"stat.swimOneCm":8,"stat.mobKills":1,"stat.sprintOneCm":1436}